setup.py
pytest_mozwebqa/__init__.py
pytest_mozwebqa/credentials.py
pytest_mozwebqa/html_report.py
pytest_mozwebqa/pytest_mozwebqa.py
pytest_mozwebqa/sauce_labs.py
pytest_mozwebqa/selenium_client.py
pytest_mozwebqa.egg-info/PKG-INFO
pytest_mozwebqa.egg-info/SOURCES.txt
pytest_mozwebqa.egg-info/dependency_links.txt
pytest_mozwebqa.egg-info/entry_points.txt
pytest_mozwebqa.egg-info/pbr.json
pytest_mozwebqa.egg-info/requires.txt
pytest_mozwebqa.egg-info/top_level.txt
pytest_mozwebqa/resources/jquery.js
pytest_mozwebqa/resources/main.js
pytest_mozwebqa/resources/style.css