Metadata-Version: 1.1
Name: pytest-mozwebqa
Version: 1.6
Summary: Mozilla WebQA plugin for py.test.
Home-page: https://github.com/mozilla/pytest-mozwebqa
Author: Dave Hunt
Author-email: dhunt@mozilla.com
License: Mozilla Public License 2.0 (MPL 2.0)
Keywords: py.test pytest selenium saucelabs mozwebqa webqa qa mozilla
Platform: UNKNOWN
Classifier: Development Status :: 5 - Production/Stable
Classifier: Intended Audience :: Developers
Classifier: License :: OSI Approved :: Mozilla Public License 2.0 (MPL 2.0)
Classifier: Operating System :: POSIX
Classifier: Operating System :: Microsoft :: Windows
Classifier: Operating System :: MacOS :: MacOS X
Classifier: Topic :: Software Development :: Quality Assurance
Classifier: Topic :: Software Development :: Testing
Classifier: Topic :: Utilities
Classifier: Programming Language :: Python
Classifier: Programming Language :: Python :: 2.6
Classifier: Programming Language :: Python :: 2.7
